Workbook

Sheet Instructions
A1: SUBCONTRACTOR, VENDOR & LICENSE TRACKER — INSTRUCTIONS
A2: v2.0 Program • Flat table architecture • Designed for SharePoint + Copilot App Builder or Cowork
A4: SHEET / TABLE NAME | B4: PURPOSE | C4: OWNER & CADENCE
A5: Vendor Register → Table: VendorRegister | B5: One row per vendor/subcontractor. Master data including agreement type, PoP, payment terms, contact. Ceiling, funded, and burn auto-calculate from ModLog and InvoiceLog via SUMIF/MAXIFS keyed on Vendor ID. | C5: Contracts Lead — update when vendor added, agreement changes, or status changes.
A6: Mod Log → Table: ModLog | B6: One row per modification across ALL vendors. Vendor ID links each mod to the Vendor Register. Tracks From → By → To for ceiling and funded independently. Admin mods carry $0 financial changes. This table drives ceiling and funded values on the register. | C6: Contracts Lead — log at point of mod execution, never retroactively.
A7: Invoice Log → Table: InvoiceLog | B7: One row per invoice across ALL vendors. PM enters invoice number, date submitted, period, amount, and approval status as each invoice arrives. Only Approved invoices count toward burn on the Vendor Register. Cumulative totals auto-calculate. | C7: PM — enter at invoice receipt. Update status when approved.
A8: License & Subscription Register → Table: LicenseRegister | B8: One row per software license or SaaS subscription. Tracks vendor, product, seats, annual cost, expiry date, auto-renew flag, and days to renewal. Color alerts at <90 days (yellow) and <30 days / expired (red). | C8: Program Control / Tech Lead — update at procurement or renewal.
A9: Summary Dashboard | B9: Auto-calculated program-level view. Vendor financial health, funding alerts, agreement expiration pipeline, and license renewal pipeline. Do not edit directly — all values pull from the four tables above. | C9: PM — read only. Refresh by opening file if on SharePoint.
A11: WHY FLAT TABLES — KEY DESIGN DECISIONS
A12: Vendor ID as the link key | B12: Every row in ModLog and InvoiceLog carries a Vendor ID (e.g. V-001). The Vendor Register uses MAXIFS and SUMIF keyed on Vendor ID to pull ceiling, funded, and burn automatically. Adding a new vendor = one new row on the register and a Vendor ID to use in future mods and invoices. No new tabs, no formula updates, no dashboard changes.
A13: Excel Tables (not plain ranges) | B13: Each data range is defined as a named Excel Table (VendorRegister, ModLog, InvoiceLog, LicenseRegister). Excel Tables expand automatically as rows are added. Copilot App Builder and Power Automate connect to named tables directly — no brittle range references. Cowork reads them the same way.
A14: Only Approved invoices count toward burn | B14: The Vendor Register sums invoices where Status = Approved. Pending invoices are visible in the Invoice Log but do not move the burn number until PM approval. This prevents premature burn reporting.
A15: Ceiling and funded are independent | B15: A mod can increase the ceiling without adding funded value (ceiling raise pending incremental funding), or add funded value without changing the ceiling (incremental funding against existing ceiling). The From → By → To columns on ModLog track each independently.
A17: MOD TYPE DEFINITIONS
A18: MOD TYPE / CATEGORY | B18: DESCRIPTION — A SINGLE MOD CAN APPLY MULTIPLE CATEGORIES
A19: Award | B19: Initial contract award. Establishes base ceiling, funded value, PoP, and scope. Every vendor starts with one Award. Categories field = 'Award'.
A20: Ceiling | B20: Mod increases or decreases the not-to-exceed ceiling. The Ceiling From → By → To columns capture the change. Can appear alone or combined with Funding or Scope.
A21: Funding | B21: Mod adds or removes funded value (obligated dollars) without necessarily changing the ceiling. Common on incrementally funded agreements. Can appear alone or combined with Ceiling or PoP.
A22: PoP | B22: Mod extends or shortens the period of performance end date. Can appear alone (pure time extension) or combined with Ceiling and/or Funding when additional resources accompany the extension.
A23: Scope | B23: Mod adds, removes, or modifies the statement of work. May carry financial and schedule impact (combine with Ceiling, Funding, PoP as applicable) or may be cost-neutral.
A24: Admin | B24: No financial, schedule, or scope change. Use for POC updates, address changes, key personnel substitutions, novation, and similar administrative actions. When Admin is the only category, all financial From/By/To fields should be $0.
A25: EXAMPLES OF MULTI-CATEGORY MODS
A26: Ceiling, Funding | B26: Ceiling raised AND additional dollars obligated in the same mod — the most common combined mod.
A27: Ceiling, Funding, PoP | B27: Full extension mod: more time, higher ceiling, more funding.
A28: Funding, PoP | B28: Time extension with incremental funding but no ceiling change.
A29: Scope, Ceiling, Funding | B29: Scope addition that requires ceiling and funding increase.
A30: Scope, Admin | B30: SOW clarification with no financial impact — also administrative in nature.

Sheet Vendor Register
A1: VENDOR REGISTER [Table: VendorRegister]
A2: One row per vendor • Ceiling and Funded auto-calculate from Mod Log • Burn auto-calculates from Invoice Log • TO ADD A NEW VENDOR: copy the green template row, paste below last vendor, fill in static fields only
A3: Vendor ID | B3: Company Name | C3: Vendor Type | D3: Primary Agmt Type | E3: Agmt Number | F3: Payment Terms | G3: PoP Start | H3: PoP End | I3: Days to PoP End | J3: Branch Supporting | K3: POC Name | L3: POC Email | M3: NDA On File | N3: NDA Expiry | O3: Current Ceiling ($) | P3: Current Funded ($) | Q3: Invoiced Approved ($) | R3: Remaining Funded ($) | S3: % Burned (Funded) | T3: % Burned (Ceiling) | U3: Funding Health | V3: Agreement Status
A4: Format: V-001 | B4: Company legal name | C4: Subcontractor or Vendor | D4: SUBK / MSA / PO / TO / MSA | E4: Agreement number | F4: Net 30 Net 45 etc. | G4: MM/DD/YYYY | H4: MM/DD/YYYY | I4: AUTO → formula | J4: Branch name | K4: Full name | L4: email@domain.com | M4: Yes / No | N4: MM/DD/YYYY | O4: AUTO → Mod Log | P4: =IFERROR(_xlfn.MAXIFS('Mod Log'!$M:$M,'Mod Log'!$A:$A,A4),0) -> 0 | Q4: AUTO → Invoice Log | R4: AUTO → formula | S4: AUTO → formula | T4: AUTO → formula | U4: AUTO → formula | V4: Active / Pending / Closed
A5: ▶ TEMPLATE — copy this row for new vendor, do not edit formulas | B5: [Company Name] | C5: Subcontractor | D5: SUBK | E5: [Agmt #] | F5: Net 30 | I5: =IF(N(H5)+IFERROR(DATEVALUE(H5),0)=0,"—",IF(ISNUMBER(H5),H5,DATEVALUE(H5))-TODAY()) -> — | J5: [Branch] | K5: [POC Name] | L5: [POC Email] | M5: Yes | O5: =IFERROR(_xludf.maxifs('Mod Log'!$J:$J,'Mod Log'!$A:$A,A5),0) -> 0 | P5: =IFERROR(_xlfn.MAXIFS('Mod Log'!$M:$M,'Mod Log'!$A:$A,A5),0) -> 0 | Q5: =SUMIFS('Invoice Log'!$F:$F,'Invoice Log'!$A:$A,A5,'Invoice Log'!$G:$G,"Approved") -> 0 | R5: =P5-Q5 -> 0 | S5: =IF(P5>0,Q5/P5,0) -> 0 | T5: =IF(O5>0,Q5/O5,0) -> 0 | U5: =IF(P5=0,"—",IF(S5>=0.9,"🔴 Critical — Near Cap",IF(S5>=0.75,"🟡 Warning — >75% Burned","🟢 Healthy"))) -> — | V5: Active
A6: V-001 | B6: Apex Solutions LLC | C6: Subcontractor | D6: SUBK | E6: SUBK-001 | F6: Net 30 | G6: 46113 | H6: 46477 | I6: =IF(N(H6)+IFERROR(DATEVALUE(H6),0)=0,"—",IF(ISNUMBER(H6),H6,DATEVALUE(H6))-TODAY()) -> 281 | J6: 2.0 Software Dev | K6: John Carter | L6: jcarter@apex.com | M6: Yes | N6: 12/31/2027 | O6: =IFERROR(_xludf.maxifs('Mod Log'!$J:$J,'Mod Log'!$A:$A,A6),0) -> 0 | P6: =IFERROR(_xlfn.MAXIFS('Mod Log'!$M:$M,'Mod Log'!$A:$A,A6),0) -> 150000 | Q6: =SUMIFS('Invoice Log'!$F:$F,'Invoice Log'!$A:$A,A6,'Invoice Log'!$G:$G,"Approved") -> 60700 | R6: =P6-Q6 -> 89300 | S6: =IF(P6>0,Q6/P6,0) -> 0.40466667 | T6: =IF(O6>0,Q6/O6,0) -> 0 | U6: =IF(P6=0,"—",IF(S6>=0.9,"🔴 Critical — Near Cap",IF(S6>=0.75,"🟡 Warning — >75% Burned","🟢 Healthy"))) -> 🟢 Healthy | V6: Active
A7: V-002 | B7: CyberShield Inc. | C7: Subcontractor | D7: SUBK | E7: SUBK-002 | F7: Net 30 | G7: 46113 | H7: 46295 | I7: =IF(N(H7)+IFERROR(DATEVALUE(H7),0)=0,"—",IF(ISNUMBER(H7),H7,DATEVALUE(H7))-TODAY()) -> 99 | J7: 3.0 Security & Compliance | K7: Maria Lopez | L7: mlopez@cybershield.com | M7: Yes | N7: 12/31/2027 | O7: =IFERROR(_xludf.maxifs('Mod Log'!$J:$J,'Mod Log'!$A:$A,A7),0) -> 0 | P7: =IFERROR(_xlfn.MAXIFS('Mod Log'!$M:$M,'Mod Log'!$A:$A,A7),0) -> 80000 | Q7: =SUMIFS('Invoice Log'!$F:$F,'Invoice Log'!$A:$A,A7,'Invoice Log'!$G:$G,"Approved") -> 33000 | R7: =P7-Q7 -> 47000 | S7: =IF(P7>0,Q7/P7,0) -> 0.4125 | T7: =IF(O7>0,Q7/O7,0) -> 0 | U7: =IF(P7=0,"—",IF(S7>=0.9,"🔴 Critical — Near Cap",IF(S7>=0.75,"🟡 Warning — >75% Burned","🟢 Healthy"))) -> 🟢 Healthy | V7: Active
A8: V-003 | B8: CloudInfra Partners | C8: Subcontractor | D8: MSA | E8: MSA-001 | F8: Net 45 | G8: 46023 | H8: 46387 | I8: =IF(N(H8)+IFERROR(DATEVALUE(H8),0)=0,"—",IF(ISNUMBER(H8),H8,DATEVALUE(H8))-TODAY()) -> 191 | J8: 4.0 Infra & Environment | K8: David Kim | L8: dkim@cloudinfra.com | M8: Yes | N8: 12/31/2027 | O8: =IFERROR(_xludf.maxifs('Mod Log'!$J:$J,'Mod Log'!$A:$A,A8),0) -> 0 | P8: =IFERROR(_xlfn.MAXIFS('Mod Log'!$M:$M,'Mod Log'!$A:$A,A8),0) -> 60000 | Q8: =SUMIFS('Invoice Log'!$F:$F,'Invoice Log'!$A:$A,A8,'Invoice Log'!$G:$G,"Approved") -> 16000 | R8: =P8-Q8 -> 44000 | S8: =IF(P8>0,Q8/P8,0) -> 0.26666667 | T8: =IF(O8>0,Q8/O8,0) -> 0 | U8: =IF(P8=0,"—",IF(S8>=0.9,"🔴 Critical — Near Cap",IF(S8>=0.75,"🟡 Warning — >75% Burned","🟢 Healthy"))) -> 🟢 Healthy | V8: Active
A9: V-004 | B9: TrainingPro LLC | C9: Vendor | D9: PO | E9: PO-001 | F9: Net 30 | G9: 46143 | H9: 46326 | I9: =IF(N(H9)+IFERROR(DATEVALUE(H9),0)=0,"—",IF(ISNUMBER(H9),H9,DATEVALUE(H9))-TODAY()) -> 130 | J9: 6.0 Fielding & Transition | K9: Sarah Chen | L9: schen@trainingpro.com | M9: Yes | N9: 46207 | O9: =IFERROR(_xludf.maxifs('Mod Log'!$J:$J,'Mod Log'!$A:$A,A9),0) -> 0 | P9: =IFERROR(_xlfn.MAXIFS('Mod Log'!$M:$M,'Mod Log'!$A:$A,A9),0) -> 35000 | Q9: =SUMIFS('Invoice Log'!$F:$F,'Invoice Log'!$A:$A,A9,'Invoice Log'!$G:$G,"Approved") -> 0 | R9: =P9-Q9 -> 35000 | S9: =IF(P9>0,Q9/P9,0) -> 0 | T9: =IF(O9>0,Q9/O9,0) -> 0 | U9: =IF(P9=0,"—",IF(S9>=0.9,"🔴 Critical — Near Cap",IF(S9>=0.75,"🟡 Warning — >75% Burned","🟢 Healthy"))) -> 🟢 Healthy | V9: Active
A10: V-005 | B10: DataBridge Consulting | C10: Subcontractor | D10: SUBK | E10: SUBK-003 | F10: Net 30 | G10: 46113 | H10: 46477 | I10: =IF(N(H10)+IFERROR(DATEVALUE(H10),0)=0,"—",IF(ISNUMBER(H10),H10,DATEVALUE(H10))-TODAY()) -> 281 | J10: 2.0 Software Dev | K10: Mike Torres | L10: mtorres@databridge.com | M10: Yes | N10: 12/31/2027 | O10: =IFERROR(_xludf.maxifs('Mod Log'!$J:$J,'Mod Log'!$A:$A,A10),0) -> 0 | P10: =IFERROR(_xlfn.MAXIFS('Mod Log'!$M:$M,'Mod Log'!$A:$A,A10),0) -> 90000 | Q10: =SUMIFS('Invoice Log'!$F:$F,'Invoice Log'!$A:$A,A10,'Invoice Log'!$G:$G,"Approved") -> 50500 | R10: =P10-Q10 -> 39500 | S10: =IF(P10>0,Q10/P10,0) -> 0.56111111 | T10: =IF(O10>0,Q10/O10,0) -> 0 | U10: =IF(P10=0,"—",IF(S10>=0.9,"🔴 Critical — Near Cap",IF(S10>=0.75,"🟡 Warning — >75% Burned","🟢 Healthy"))) -> 🟢 Healthy | V10: Active
A11: V-006 | B11: Test | C11: Subcontractor | D11: SUBK | E11: [Agmt #] | F11: Net 30 | I11: =IF(N(H11)+IFERROR(DATEVALUE(H11),0)=0,"—",IF(ISNUMBER(H11),H11,DATEVALUE(H11))-TODAY()) -> — | K11: [POC Name] | L11: [POC Email] | M11: Yes | N11: 46203 | O11: =IFERROR(_xlfn.SINGLE(_xlfn.MAXIFS('Mod Log'!$J:$J,'Mod Log'!$A:$A,A11)),0) -> 30000 | P11: =IFERROR(_xlfn.MAXIFS('Mod Log'!$M:$M,'Mod Log'!$A:$A,A11),0) -> 30000 | Q11: =SUMIFS('Invoice Log'!$F:$F,'Invoice Log'!$A:$A,A11,'Invoice Log'!$G:$G,"Approved") -> 50000 | R11: =P11-Q11 -> -20000 | S11: =IF(P11>0,Q11/P11,0) -> 1.6666667 | T11: =IF(O11>0,Q11/O11,0) -> 1.6666667 | U11: =IF(P11=0,"—",IF(S11>=0.9,"🔴 Critical — Near Cap",IF(S11>=0.75,"🟡 Warning — >75% Burned","🟢 Healthy"))) -> 🔴 Critical — Near Cap | V11: Active

Sheet Mod Log
A1: MOD LOG — ALL VENDORS [Table: ModLog]
A2: One row per modification across all vendors • Vendor ID links to Vendor Register • Categories: comma-separate all that apply (e.g. 'Ceiling, Funding, PoP') • From → By → To tracks ceiling and funded independently
A3: Vendor ID | B3: Company Name | C3: Agmt Number | D3: Mod Number | E3: Effective Date | F3: Mod Categories (select all that apply) | G3: Description | H3: Ceiling From ($) | I3: Ceiling By ($) | J3: Ceiling To ($) | K3: Funded From ($) | L3: Funded By ($) | M3: Funded To ($) | N3: Previous PoP End | O3: New PoP End | P3: Approved By | Q3: Notes
A4: V-001 | B4: Apex Solutions LLC | C4: SUBK-001 | D4: Mod-000 | E4: 04/01/2026 | F4: Award | G4: Initial subcontract award. | H4: 0 | I4: 200000 | J4: 200000 | K4: 0 | L4: 150000 | M4: 150000 | O4: 03/31/2027 | P4: Contracting Officer | Q4: Base award.
A5: V-001 | B5: Apex Solutions LLC | C5: SUBK-001 | D5: Mod-001 | E5: 06/10/2026 | F5: Ceiling, Funding | G5: Scope addition CR-001 (mobile UI). Ceiling raised $50K; no new funding added at this time. | H5: 200000 | I5: 50000 | J5: 250000 | K5: 150000 | L5: 0 | M5: 150000 | N5: 03/31/2027 | O5: 03/31/2027 | P5: Contracting Officer | Q5: Tied to CR-001. MOD-001 executed 06/10.
A6: V-002 | B6: CyberShield Inc. | C6: SUBK-002 | D6: Mod-000 | E6: 04/01/2026 | F6: Award | G6: Initial subcontract award — ATO support and STIG remediation. | H6: 0 | I6: 80000 | J6: 80000 | K6: 0 | L6: 80000 | M6: 80000 | O6: 09/30/2026 | P6: Contracting Officer | Q6: Base award.
A7: V-002 | B7: CyberShield Inc. | C7: SUBK-002 | D7: Mod-001 | E7: TBD | F7: PoP | G7: 30-day PoP extension per CR-002. No financial change. Pending CO signature. | H7: 80000 | I7: 0 | J7: 80000 | K7: 80000 | L7: 0 | M7: 80000 | N7: 09/30/2026 | O7: 10/31/2026 | P7: PM / CO | Q7: Pending. CR-002 still awaiting government approval.
A8: V-003 | B8: CloudInfra Partners | C8: MSA-001 | D8: Mod-000 | E8: 01/01/2026 | F8: Award | G8: MSA award — cloud environment provisioning and maintenance. | H8: 0 | I8: 120000 | J8: 120000 | K8: 0 | L8: 60000 | M8: 60000 | O8: 12/31/2026 | P8: Contracting Officer | Q8: Base award.
A9: V-003 | B9: CloudInfra Partners | C9: MSA-001 | D9: Mod-001 | E9: 06/20/2026 | F9: Scope | G9: Added GFE configuration support per CR-004. No ceiling or funding change. | H9: 120000 | I9: 0 | J9: 120000 | K9: 60000 | L9: 0 | M9: 60000 | N9: 12/31/2026 | O9: 12/31/2026 | P9: PM | Q9: Scope only — no financial impact.
A10: V-004 | B10: TrainingPro LLC | C10: PO-001 | D10: Mod-000 | E10: 05/01/2026 | F10: Award | G10: PO award — training development and delivery. | H10: 0 | I10: 35000 | J10: 35000 | K10: 0 | L10: 35000 | M10: 35000 | O10: 10/31/2026 | P10: PM | Q10: Base award.
A11: V-005 | B11: DataBridge Consulting | C11: SUBK-003 | D11: Mod-000 | E11: 04/01/2026 | F11: Award | G11: Initial subcontract award — API integration and data layer. | H11: 0 | I11: 180000 | J11: 180000 | K11: 0 | L11: 90000 | M11: 90000 | O11: 03/31/2027 | P11: Contracting Officer | Q11: Base award.
F12: Ceiling, Funding, PoP | G12: [Enter description] | H12: 0 | I12: 0 | J12: 0 | K12: 0 | L12: 0 | M12: 0
A13: V-006 | B13: Test | D13: MOD-000 | E13: 46022 | F13: Award | G13: [Description of what this mod does and why] | H13: 0 | I13: 30000 | J13: 30000 | K13: 0 | L13: 30000 | M13: 30000 | P13: [Approver name + title] | Q13: [Any additional context]
A14: ▶ NEW MOD ENTRY ROW — fill in all fields, copy down for additional mods | B14: [Company Name] | C14: [Agmt #] | D14: [Mod-00X] | E14: [MM/DD/YYYY] | F14: Award / Ceiling / Funding / PoP / Scope / Admin (comma-separate multiples) | G14: [Description of what this mod does and why] | H14: 0 | I14: 0 | J14: 0 | K14: 0 | L14: 0 | M14: 0 | N14: [prev PoP end or blank] | O14: [new PoP end or blank] | P14: [Approver name + title] | Q14: [Any additional context]

Sheet Invoice Log
A1: INVOICE LOG — ALL VENDORS [Table: InvoiceLog]
A2: One row per invoice across all vendors • PM enters: Vendor ID, Invoice #, Date, Period, Amount, Status • Only Approved invoices count toward burn on Vendor Register • Cumulative totals auto-calculate per row
A3: Vendor ID | B3: Company Name | C3: Invoice Number | D3: Date Submitted | E3: Period of Performance | F3: Invoice Amount ($) | G3: Approval Status | H3: PM Approved By | I3: Date Approved | J3: Cumul. Approved This Vendor ($) | K3: Notes
A4: V-001 | B4: Apex Solutions LLC | C4: INV-001-001 | D4: 04/30/2026 | E4: April 2026 Services | F4: 24500 | G4: Approved | H4: PM | I4: 05/05/2026 | J4: =SUMIFS($F$4:F4,$A$4:A4,A4,$G$4:G4,"Approved") -> 24500
A5: V-001 | B5: Apex Solutions LLC | C5: INV-001-002 | D5: 05/31/2026 | E5: May 2026 Services | F5: 36200 | G5: Approved | H5: PM | I5: 06/04/2026 | J5: =SUMIFS($F$4:F5,$A$4:A5,A5,$G$4:G5,"Approved") -> 60700
A6: V-001 | B6: Apex Solutions LLC | C6: INV-001-003 | D6: 06/23/2026 | E6: June 2026 Services | F6: 37300 | G6: Pending | J6: =SUMIFS($F$4:F6,$A$4:A6,A6,$G$4:G6,"Approved") -> 60700 | K6: Awaiting PM review.
A7: V-002 | B7: CyberShield Inc. | C7: INV-002-001 | D7: 04/30/2026 | E7: April 2026 Services | F7: 15000 | G7: Approved | H7: PM | I7: 05/05/2026 | J7: =SUMIFS($F$4:F7,$A$4:A7,A7,$G$4:G7,"Approved") -> 15000
A8: V-002 | B8: CyberShield Inc. | C8: INV-002-002 | D8: 05/31/2026 | E8: May 2026 Services | F8: 18000 | G8: Approved | H8: PM | I8: 06/04/2026 | J8: =SUMIFS($F$4:F8,$A$4:A8,A8,$G$4:G8,"Approved") -> 33000
A9: V-002 | B9: CyberShield Inc. | C9: INV-002-003 | D9: 06/23/2026 | E9: June 2026 Services | F9: 12000 | G9: Pending | J9: =SUMIFS($F$4:F9,$A$4:A9,A9,$G$4:G9,"Approved") -> 33000 | K9: Awaiting PM review.
A10: V-003 | B10: CloudInfra Partners | C10: INV-003-001 | D10: 04/30/2026 | E10: April 2026 Services | F10: 8000 | G10: Approved | H10: PM | I10: 05/05/2026 | J10: =SUMIFS($F$4:F10,$A$4:A10,A10,$G$4:G10,"Approved") -> 8000
A11: V-003 | B11: CloudInfra Partners | C11: INV-003-002 | D11: 05/31/2026 | E11: May 2026 Services | F11: 8000 | G11: Approved | H11: PM | I11: 06/04/2026 | J11: =SUMIFS($F$4:F11,$A$4:A11,A11,$G$4:G11,"Approved") -> 16000
A12: V-003 | B12: CloudInfra Partners | C12: INV-003-003 | D12: 06/23/2026 | E12: June 2026 Services | F12: 6000 | G12: Pending | J12: =SUMIFS($F$4:F12,$A$4:A12,A12,$G$4:G12,"Approved") -> 16000 | K12: Awaiting PM review.
A13: V-005 | B13: DataBridge Consulting | C13: INV-005-001 | D13: 04/30/2026 | E13: April 2026 Services | F13: 22000 | G13: Approved | H13: PM | I13: 05/05/2026 | J13: =SUMIFS($F$4:F13,$A$4:A13,A13,$G$4:G13,"Approved") -> 22000
A14: V-005 | B14: DataBridge Consulting | C14: INV-005-002 | D14: 05/31/2026 | E14: May 2026 Services | F14: 28500 | G14: Approved | H14: PM | I14: 06/04/2026 | J14: =SUMIFS($F$4:F14,$A$4:A14,A14,$G$4:G14,"Approved") -> 50500
A15: V-005 | B15: DataBridge Consulting | C15: INV-005-003 | D15: 06/23/2026 | E15: June 2026 Services | F15: 28000 | G15: Pending | J15: =SUMIFS($F$4:F15,$A$4:A15,A15,$G$4:G15,"Approved") -> 50500 | K15: Awaiting PM review.
G16: Pending | J16: =SUMIFS($F$4:F16,$A$4:A16,A16,$G$4:G16,"Approved") -> 0
A17: v-006 | B17: Test | C17: INV-004-001 | D17: 46207 | E17: [Month YYYY Services] | F17: 50000 | G17: Approved | J17: =SUMIFS($F$4:F17,$A$4:A17,A17,$G$4:G17,"Approved") -> 50000
A18: ▶ NEW INVOICE ENTRY ROW | B18: [Company Name] | C18: [INV-00X-00X] | D18: [MM/DD/YYYY] | E18: [Month YYYY Services] | F18: 0 | G18: Pending | J18: =SUMIFS($F$4:F18,$A$4:A18,A18,$G$4:G18,"Approved") -> 0

Sheet License & Subscription Register
A1: LICENSE & SUBSCRIPTION REGISTER [Table: LicenseRegister]
A2: One row per software license or SaaS subscription • Renewal alerts: <90 days = yellow, <30 days or expired = red • Add new license = add one row
A3: License ID | B3: Vendor | C3: Product / Service | D3: Category | E3: License Type | F3: # Seats / Units | G3: Branch Using | H3: Annual Cost ($) | I3: Total Contract ($) | J3: Purchase Date | K3: Expiry Date | L3: Days to Renewal | M3: Auto- Renew? | N3: Renewal Action Required | O3: PO / Ref # | P3: Subscription POC Name | Q3: Subscription POC Email
A4: L-001 | B4: Microsoft | C4: Microsoft 365 E3 | D4: Productivity | E4: Subscription | F4: 15 | G4: All Branches | H4: 6000 | I4: 6000 | J4: 01/01/2026 | K4: 12/31/2026 | L4: =IF(ISNUMBER(K4),K4-TODAY(),"—") -> — | M4: Yes | N4: Confirm seat count before renewal | O4: PO-M365-001 | P4: IT Admin | Q4: m365support@microsoft.com
A5: L-002 | B5: ClickUp | C5: ClickUp Business | D5: Project Mgmt | E5: Subscription | F5: 12 | G5: 1.0 / 2.0 | H5: 2160 | I5: 2160 | J5: 04/01/2026 | K5: 03/31/2027 | L5: =IF(ISNUMBER(K5),K5-TODAY(),"—") -> — | M5: Yes | N5: Verify IT governance approval before renew | O5: PO-CU-001 | P5: PM | Q5: support@clickup.com
A6: L-003 | B6: GitHub | C6: GitHub Enterprise | D6: Dev Tools | E6: Subscription | F6: 8 | G6: 2.0 Software Dev | H6: 3840 | I6: 3840 | J6: 04/01/2026 | K6: 03/31/2027 | L6: =IF(ISNUMBER(K6),K6-TODAY(),"—") -> — | M6: Yes | N6: Review seat count at renewal | O6: PO-GH-001 | P6: Dev Lead | Q6: enterprise@github.com
A7: L-004 | B7: Tenable | C7: Tenable.io Vuln Mgmt | D7: Security | E7: Subscription | F7: 1 | G7: 3.0 Security | H7: 18500 | I7: 18500 | J7: 06/01/2026 | K7: 05/31/2027 | L7: =IF(ISNUMBER(K7),K7-TODAY(),"—") -> — | M7: No | N7: CO approval required — start process 90 days out | O7: PO-TEN-001 | P7: Security Lead | Q7: renewals@tenable.com
A8: L-005 | B8: AWS | C8: AWS GovCloud | D8: Cloud Infra | E8: Consumption | F8: 1 | G8: 4.0 Infra | H8: 24000 | I8: 24000 | J8: 04/01/2026 | K8: 03/31/2027 | L8: =IF(ISNUMBER(K8),K8-TODAY(),"—") -> — | M8: Yes | N8: Review monthly spend vs. budget | O8: AWS-GOV-001 | P8: Infra Lead | Q8: aws-enterprise@amazon.com
A9: L-006 | B9: Atlassian | C9: Jira Software | D9: Dev Tools | E9: Subscription | F9: 10 | G9: 2.0 Software Dev | H9: 1500 | I9: 1500 | J9: 01/01/2026 | K9: 07/15/2026 | L9: =IF(ISNUMBER(K9),K9-TODAY(),"—") -> — | M9: Yes | N9: EXPIRING <30 DAYS — action required now | O9: PO-JIR-001 | P9: Dev Lead | Q9: renewals@atlassian.com
A10: L-007 | B10: Fortify | C10: Fortify SAST | D10: Security | E10: Annual License | F10: 1 | G10: 3.0 Security | H10: 12000 | I10: 12000 | J10: 07/01/2025 | K10: 06/30/2026 | L10: =IF(ISNUMBER(K10),K10-TODAY(),"—") -> — | M10: No | N10: EXPIRED — renew immediately | O10: PO-FRT-001 | P10: Security Lead | Q10: renewals@microfocus.com
A11: L-008 | B11: Zoom | C11: Zoom Business | D11: Comms | E11: Subscription | F11: 20 | G11: All Branches | H11: 3840 | I11: 3840 | J11: 03/01/2026 | K11: 02/28/2027 | L11: =IF(ISNUMBER(K11),K11-TODAY(),"—") -> — | M11: Yes | N11: Standard renewal | O11: PO-ZM-001 | P11: PM | Q11: enterprise@zoom.us
A12: L-009 | B12: [New Tool] | E12: Subscription | F12: 0 | H12: 0 | I12: 0 | L12: =IF(ISNUMBER(K12),K12-TODAY(),"—") -> —

Sheet Summary Dashboard
A1: SUMMARY DASHBOARD
A2: Auto-calculated from VendorRegister, ModLog, InvoiceLog, and LicenseRegister tables • Do not edit directly
A4: PROGRAM-LEVEL SUBCONTRACTOR FINANCIAL SUMMARY
A5: Metric | B5: Value
A6: Total Subcontractor Ceiling | B6: =SUMIF('Vendor Register'!$V:$V,"Active",'Vendor Register'!$O:$O) -> 30000
A7: Total Funded Value | B7: =SUMIF('Vendor Register'!$V:$V,"Active",'Vendor Register'!$P:$P) -> 445000
A8: Total Invoiced (Approved) | B8: =SUMIF('Vendor Register'!$V:$V,"Active",'Vendor Register'!$Q:$Q) -> 210200
A9: Total Remaining Funded | B9: =SUMIF('Vendor Register'!$V:$V,"Active",'Vendor Register'!$R:$R) -> 234800
A10: Program Burn % (vs Funded) | B10: =IFERROR(SUMIF('Vendor Register'!$V:$V,"Active",'Vendor Register'!$Q:$Q)/SUMIF('Vendor Register'!$V:$V,"Active",'Vendor Register'!$P:$P),0) -> 0.47235955
A11: Vendors at Warning (>75%) | B11: =COUNTIF('Vendor Register'!$U:$U,"🟡*") -> 0
A12: Vendors at Critical (>90%) | B12: =COUNTIF('Vendor Register'!$U:$U,"🔴*") -> 1
A13: Total Annual License Spend | B13: =SUM('License & Subscription Register'!$H:$H) -> 71840
A15: VENDOR FINANCIAL HEALTH — ALL ACTIVE VENDORS
A16: Vendor ID | B16: Company | C16: Ceiling ($) | D16: Funded ($) | E16: Invoiced Approved ($) | F16: Remaining Funded ($) | G16: Funding Health
A17: ='Vendor Register'!A4 -> Format: V-001 | B17: ='Vendor Register'!B4 -> Company legal name | C17: ='Vendor Register'!O4 -> AUTO → Mod Log | D17: ='Vendor Register'!P4 -> 0 | E17: ='Vendor Register'!Q4 -> AUTO → Invoice Log | F17: ='Vendor Register'!R4 -> AUTO → formula | G17: ='Vendor Register'!U4 -> AUTO → formula
A18: ='Vendor Register'!A5 -> ▶ TEMPLATE — copy this row for new vendor, do not edit formulas | B18: ='Vendor Register'!B5 -> [Company Name] | C18: ='Vendor Register'!O5 -> 0 | D18: ='Vendor Register'!P5 -> 0 | E18: ='Vendor Register'!Q5 -> 0 | F18: ='Vendor Register'!R5 -> 0 | G18: ='Vendor Register'!U5 -> —
A19: ='Vendor Register'!A6 -> V-001 | B19: ='Vendor Register'!B6 -> Apex Solutions LLC | C19: ='Vendor Register'!O6 -> 0 | D19: ='Vendor Register'!P6 -> 150000 | E19: ='Vendor Register'!Q6 -> 60700 | F19: ='Vendor Register'!R6 -> 89300 | G19: ='Vendor Register'!U6 -> 🟢 Healthy
A20: ='Vendor Register'!A7 -> V-002 | B20: ='Vendor Register'!B7 -> CyberShield Inc. | C20: ='Vendor Register'!O7 -> 0 | D20: ='Vendor Register'!P7 -> 80000 | E20: ='Vendor Register'!Q7 -> 33000 | F20: ='Vendor Register'!R7 -> 47000 | G20: ='Vendor Register'!U7 -> 🟢 Healthy
A21: ='Vendor Register'!A8 -> V-003 | B21: ='Vendor Register'!B8 -> CloudInfra Partners | C21: ='Vendor Register'!O8 -> 0 | D21: ='Vendor Register'!P8 -> 60000 | E21: ='Vendor Register'!Q8 -> 16000 | F21: ='Vendor Register'!R8 -> 44000 | G21: ='Vendor Register'!U8 -> 🟢 Healthy
A22: TOTALS | C22: =SUM(C17:C21) -> 0 | D22: =SUM(D17:D21) -> 290000 | E22: =SUM(E17:E21) -> 109700 | F22: =SUM(F17:F21) -> 180300
A24: AGREEMENT EXPIRATION ALERTS (PoP End < 90 Days)
A25: Vendor ID | B25: Company | C25: Agmt Type | D25: Agmt Number | E25: PoP End | F25: Days Remaining | G25: Status
A26: V-002 | B26: CyberShield Inc. | C26: SUBK | D26: SUBK-002 | E26: 09/30/2026 | F26: =IF(ISNUMBER(E26),E26-TODAY(),"—") -> — | G26: Active
A27: V-004 | B27: TrainingPro LLC | C27: PO | D27: PO-001 | E27: 10/31/2026 | F27: =IF(ISNUMBER(E27),E27-TODAY(),"—") -> — | G27: Active
A29: LICENSE RENEWAL ALERTS (< 90 Days)
A30: License ID | B30: Vendor | C30: Product | D30: Expiry Date | E30: Days Remaining | F30: Annual Cost ($) | G30: Auto-Renew?
A31: L-007 | B31: Fortify | C31: Fortify SAST | D31: 06/30/2026 | E31: =IF(ISNUMBER(D31),D31-TODAY(),"—") -> — | F31: 12000 | G31: No
A32: L-006 | B32: Atlassian | C32: Jira Software | D32: 07/15/2026 | E32: =IF(ISNUMBER(D32),D32-TODAY(),"—") -> — | F32: 1500 | G32: Yes
A33: TOTAL ANNUAL LICENSE SPEND | F33: =SUM('License & Subscription Register'!$H:$H) -> 71840
